LICENSE
MANIFEST.in
README.rst
setup.py
lp/__init__.py
lp/game.py
lp/image.py
lp/server.py
lp.egg-info/PKG-INFO
lp.egg-info/SOURCES.txt
lp.egg-info/dependency_links.txt
lp.egg-info/requires.txt
lp.egg-info/top_level.txt
lp/images/A.png
lp/images/B.png
lp/images/C.png
lp/images/D.png
lp/images/E.png
lp/images/F.png
lp/images/G.png
lp/images/H.png
lp/images/I.png
lp/images/J.png
lp/images/K.png
lp/images/L.png
lp/images/M.png
lp/images/N.png
lp/images/O.png
lp/images/P.png
lp/images/Q.png
lp/images/R.png
lp/images/S.png
lp/images/T.png
lp/images/U.png
lp/images/V.png
lp/images/W.png
lp/images/X.png
lp/images/Y.png
lp/images/Z.png
lp/words/Words/de.txt
lp/words/Words/en.txt
lp/words/Words/es.txt
lp/words/Words/fr.txt
scripts/lp
scripts/lp-solver