Metadata-Version: 1.1
Name: lp
Version: 1.0.0
Summary: An aid for choosing words in Letterpress
Home-page: https://github.com/colons/lp
Author: colons
Author-email: pypi@colons.co
License: LICENSE
Platform: any
Classifier: Operating System :: OS Independent
